{
    "message": "",
    "admin_id": 165232823,
    "group_id": 188446752,
    "last_clear_logs": 1631377768.529692,
    "users": [
        {
            "name": "dshutrin",
            "id": 296431501,
            "moder": 1
        },
        {
            "name": "",
            "id": 298038782,
            "moder": 0
        },
        {
            "name": "",
            "id": 233609684,
            "moder": 0
        },
        {
            "name": "",
            "id": 664967725,
            "moder": 0
        },
        {
            "name": "",
            "id": 659314038,
            "moder": 0
        },
        {
            "name": "",
            "id": 480948337,
            "moder": 0
        },
        {
            "name": "",
            "id": 162536840,
            "moder": 0
        },
        {
            "name": "",
            "id": 608721271,
            "moder": 0
        },
        {
            "name": "",
            "id": 313292964,
            "moder": 0
        },
        {
            "name": "",
            "id": 557158906,
            "moder": 0
        },
        {
            "name": "",
            "id": 582989493,
            "moder": 0
        },
        {
            "name": "",
            "id": 642766890,
            "moder": 0
        },
        {
            "name": "",
            "id": 188632154,
            "moder": 0
        },
        {
            "name": "",
            "id": 556737257,
            "moder": 0
        },
        {
            "name": "",
            "id": 245220522,
            "moder": 0
        },
        {
            "name": "",
            "id": 403923317,
            "moder": 0
        },
        {
            "name": "",
            "id": 544246315,
            "moder": 0
        },
        {
            "name": "",
            "id": 240762441,
            "moder": 0
        },
        {
            "name": "",
            "id": 200475926,
            "moder": 0
        },
        {
            "name": "",
            "id": 445963305,
            "moder": 0
        },
        {
            "name": "",
            "id": 322615766,
            "moder": 0
        },
        {
            "name": "",
            "id": 549910624,
            "moder": 0
        },
        {
            "name": "",
            "id": 492394757,
            "moder": 0
        },
        {
            "name": "",
            "id": 276615685,
            "moder": 0
        },
        {
            "name": "",
            "id": 344194901,
            "moder": 0
        },
        {
            "name": "",
            "id": 518164452,
            "moder": 0
        },
        {
            "name": "",
            "id": 484810309,
            "moder": 0
        },
        {
            "name": "",
            "id": 420410838,
            "moder": 0
        },
        {
            "name": "",
            "id": 297829553,
            "moder": 0
        },
        {
            "name": "",
            "id": 561362759,
            "moder": 0
        },
        {
            "name": "",
            "id": 600178711,
            "moder": 0
        },
        {
            "name": "",
            "id": 551659831,
            "moder": 0
        }
    ],
    "banned": [],
    "lock_words": [],
    "history": [
        551659831,
        233609684,
        233609684,
        233609684,
        296431501,
        296431501,
        233609684,
        233609684,
        296431501,
        233609684
    ]
}